hat_trie.cpython-35m-darwin.so
hat_trie-0.3.dist-info/DESCRIPTION.rst
hat_trie-0.3.dist-info/METADATA
hat_trie-0.3.dist-info/RECORD
hat_trie-0.3.dist-info/WHEEL
hat_trie-0.3.dist-info/metadata.json
hat_trie-0.3.dist-info/top_level.txt
